{
    "Inc42": [
        {
            "title": "Indian Startup IPO Tracker 2026",
            "link": "https://inc42.com/features/indian-startup-ipo-tracker-2025/",
            "published": "Sun, 25 Jan 2026 09:30:54 +0000",
            "image_url": "https://inc42.com/cdn-cgi/image/quality=75/https://asset.inc42.com/2026/01/FTR-2-100.jpg"
        },
        {
            "title": "From Angel Tax To ESOP Stress: What Startups Want From Budget 2026",
            "link": "https://inc42.com/features/budget-2026-startups-seek-relief-on-esop-taxation-angel-tax-cases/",
            "published": "Sun, 25 Jan 2026 09:28:31 +0000",
            "image_url": "https://inc42.com/cdn-cgi/image/quality=75/https://asset.inc42.com/2026/01/FTR-2-1.jpg"
        },
        {
            "title": "PhonePe DRHP: A Look At Shareholding Pattern & Key Executives",
            "link": "https://inc42.com/buzz/phonepe-drhp-a-look-at-shareholding-pattern-key-executives/",
            "published": "Sun, 25 Jan 2026 07:19:27 +0000",
            "image_url": "https://inc42.com/cdn-cgi/image/quality=75/https://asset.inc42.com/2026/01/ftr-wtf_-1.jpg"
        },
        {
            "title": "How AI-First, Human-Centred Customer Experience Will Evolve In 2026",
            "link": "https://inc42.com/resources/how-ai-first-human-centred-customer-experience-will-evolve-in-2026/",
            "published": "Sun, 25 Jan 2026 06:23:52 +0000",
            "image_url": "https://inc42.com/cdn-cgi/image/quality=75/https://asset.inc42.com/2026/01/Untitled-design-1-2.png"
        },
        {
            "title": "Eternal\u2019s Post Deepinder Goyal Era",
            "link": "https://inc42.com/features/eternals-post-deepinder-goyal-era/",
            "published": "Sun, 25 Jan 2026 05:30:32 +0000",
            "image_url": "https://inc42.com/cdn-cgi/image/quality=75/https://asset.inc42.com/2026/01/Outline-Design.jpg"
        }
    ]
}